[
  {
    "sample_index": 899,
    "context_index": 1323513434,
    "recording_id": 14,
    "event_id": "subset_cutin_distribution_1323513434",
    "score": 27.631021115928547,
    "metrics": {
      "collision": 1.0,
      "near_collision": 1.0,
      "min_gap": 0.009885729919517416,
      "min_ttc": 0.0029381999704464847,
      "risk_score": 27.631021115928547,
      "y_long": 247.00580971549226,
      "y_cutin": 247.02132490928955,
      "evt_tail_probability": 1.951606813112646e-19,
      "physical_feasible": 1.0,
      "cutin_safety_risk_score": 246.02132490928955,
      "cutin_gap": 7.977023601531982,
      "cutin_ttc": 4.798736095428467,
      "cutin_time_headway": 0.2693396508693695,
      "cutin_lateral_time_gap": 11.100234829782842,
      "max_post_cutin_drac": 572.553466796875,
      "min_abs_lateral_offset": 0.0018524906456467063,
      "final_abs_lateral_offset": 0.22450990916684316,
      "max_lateral_approach_speed": 1.3579515865445146,
      "lateral_overlap_fraction": 0.2826086956521739,
      "is_cutin": 1.0,
      "is_front_cutin": 1.0
    }
  },
  {
    "sample_index": 1209,
    "context_index": 2068480351,
    "recording_id": 28,
    "event_id": "subset_cutin_distribution_2068480351",
    "score": 27.631021115928547,
    "metrics": {
      "collision": 1.0,
      "near_collision": 1.0,
      "min_gap": 0.001327203060014881,
      "min_ttc": 0.0003234287035147417,
      "risk_score": 27.631021115928547,
      "y_long": 417.9907941640474,
      "y_cutin": 418.01935565909776,
      "evt_tail_probability": 4.797318629197084e-22,
      "physical_feasible": 1.0,
      "cutin_safety_risk_score": 417.01935565909776,
      "cutin_gap": 9.202703475952148,
      "cutin_ttc": 2.9285573959350586,
      "cutin_time_headway": 0.3042285144329071,
      "cutin_lateral_time_gap": 6.534996256324133,
      "max_post_cutin_drac": 1000.0,
      "min_abs_lateral_offset": 0.9758196201026428,
      "final_abs_lateral_offset": 0.9758196201026428,
      "max_lateral_approach_speed": 1.0231358268857016,
      "lateral_overlap_fraction": 0.01020408163265306,
      "is_cutin": 1.0,
      "is_front_cutin": 1.0
    }
  },
  {
    "sample_index": 1301,
    "context_index": 861904496,
    "recording_id": 13,
    "event_id": "subset_cutin_distribution_0861904496",
    "score": 27.631021115928547,
    "metrics": {
      "collision": 1.0,
      "near_collision": 1.0,
      "min_gap": 0.002139096953612807,
      "min_ttc": 0.0010368010387354135,
      "risk_score": 27.631021115928547,
      "y_long": 415.97315776388996,
      "y_cutin": 416.1017202681723,
      "evt_tail_probability": 5.057028405069002e-22,
      "physical_feasible": 1.0,
      "cutin_safety_risk_score": 415.1017202681723,
      "cutin_gap": 7.469420433044434,
      "cutin_ttc": 2.007453441619873,
      "cutin_time_headway": 0.25231629610061646,
      "cutin_lateral_time_gap": 1.4367690727621238,
      "max_post_cutin_drac": 994.9691772460938,
      "min_abs_lateral_offset": 0.003509183626621545,
      "final_abs_lateral_offset": 0.621005493045397,
      "max_lateral_approach_speed": 0.7467906414903704,
      "lateral_overlap_fraction": 0.7419354838709677,
      "is_cutin": 1.0,
      "is_front_cutin": 1.0
    }
  },
  {
    "sample_index": 1639,
    "context_index": 586665026,
    "recording_id": 36,
    "event_id": "subset_cutin_distribution_0586665026",
    "score": 27.631021115928547,
    "metrics": {
      "collision": 1.0,
      "near_collision": 1.0,
      "min_gap": -0.02160604252846099,
      "min_ttc": -0.0057979095201656184,
      "risk_score": 27.631021115928547,
      "y_long": 61.794300055291956,
      "y_cutin": 61.82590574169913,
      "evt_tail_probability": 9.294787257718006e-13,
      "physical_feasible": 1.0,
      "cutin_safety_risk_score": 55.82590574169913,
      "cutin_gap": 9.714141845703125,
      "cutin_ttc": 1.782677412033081,
      "cutin_time_headway": 0.3241487145423889,
      "cutin_lateral_time_gap": 5.929019567209192,
      "max_post_cutin_drac": 97.04151153564453,
      "min_abs_lateral_offset": 0.962963174521925,
      "final_abs_lateral_offset": 0.962963174521925,
      "max_lateral_approach_speed": 0.944285305440426,
      "lateral_overlap_fraction": 0.010101010101010102,
      "is_cutin": 1.0,
      "is_front_cutin": 1.0
    }
  },
  {
    "sample_index": 1656,
    "context_index": 1819759643,
    "recording_id": 28,
    "event_id": "subset_cutin_distribution_1819759643",
    "score": 27.631021115928547,
    "metrics": {
      "collision": 1.0,
      "near_collision": 1.0,
      "min_gap": -0.12867164261734843,
      "min_ttc": -0.012528468319098448,
      "risk_score": 27.631021115928547,
      "y_long": 179.92428893436426,
      "y_cutin": 180.03788095258463,
      "evt_tail_probability": 7.019419908369704e-18,
      "physical_feasible": 1.0,
      "cutin_safety_risk_score": 174.03788095258463,
      "cutin_gap": 21.01468276977539,
      "cutin_ttc": 2.0128352642059326,
      "cutin_time_headway": 0.737828254699707,
      "cutin_lateral_time_gap": 1.7301152404323221,
      "max_post_cutin_drac": 392.39544677734375,
      "min_abs_lateral_offset": 0.00018744665421546264,
      "final_abs_lateral_offset": 0.3691088812476915,
      "max_lateral_approach_speed": 0.19704745227470988,
      "lateral_overlap_fraction": 1.0,
      "is_cutin": 1.0,
      "is_front_cutin": 1.0
    }
  }
]